mgun/__init__.py
mgun/mgun.py
mgun-0.1.8.dist-info/DESCRIPTION.rst
mgun-0.1.8.dist-info/METADATA
mgun-0.1.8.dist-info/RECORD
mgun-0.1.8.dist-info/WHEEL
mgun-0.1.8.dist-info/metadata.json
mgun-0.1.8.dist-info/top_level.txt
