Metadata-Version: 2.0
Name: mgun
Version: 0.1.8
Summary: HTTP REST Client based on requests with dynamic url building
Home-page: https://github.com/maximdanilchenko/mgun
Author: Danilchenko Maksim
Author-email: dmax.dev@gmail.com
License: MIT
Keywords: http client rest requests mgun
Platform: UNKNOWN
Classifier: Development Status :: 3 - Alpha
Classifier: Intended Audience :: Developers
Classifier: License :: OSI Approved :: MIT License
Classifier: Natural Language :: English
Classifier: Programming Language :: Python :: 2.7
Classifier: Programming Language :: Python :: 3.4
Classifier: Programming Language :: Python :: 3.5
Classifier: Programming Language :: Python :: 3.6
Requires-Dist: requests
